[
    {
        "id_usuario": 4051,
        "nombre": "Bernardo Teodoro Ocasio",
        "contrasena": "uk5tdTQ4b3E*",
        "num_telefono": "529-315-6859",
        "direccion": "Ampliacion Sur Saenz 528 Interior 982, San Pascual de la Montana, GTO 55342-0009"
    },
    {
        "id_usuario": 3549,
        "nombre": "Marcela Ivonne Barrientos",
        "contrasena": "nXmTEbJkCqfr",
        "num_telefono": "400-647-9831",
        "direccion": "Corredor Sur Sanches 648 Interior 602, Nueva Suriname, COL 60229-7819"
    },
    {
        "id_usuario": 9850,
        "nombre": "Bianca Griego Ceja",
        "contrasena": "5UyV!dqOQZK5",
        "num_telefono": "801-568-9369",
        "direccion": "Cerrada Salgado 212 Interior 274, San Celia de la Montana, PUE 38807-1167"
    },
    {
        "id_usuario": 9508,
        "nombre": "Nadia Urrutia Benavidez",
        "contrasena": "AjA67OSfzg3M",
        "num_telefono": "172-531-3631",
        "direccion": "Calle Tirado 329 440, Nueva Mexico, SLP 11461"
    },
    {
        "id_usuario": 2588,
        "nombre": "Natividad Fernando Pacheco",
        "contrasena": "T2agyPUKramu",
        "num_telefono": "755-180-2731",
        "direccion": "Avenida Timor-Leste 175 Interior 265, Vieja Dominicana, DGO 61828"
    },
    {
        "id_usuario": 8370,
        "nombre": "Genaro Rufino Padilla Padron",
        "contrasena": "GR8J6UuQRFWS",
        "num_telefono": "826-131-0932",
        "direccion": "Calle Olmos 604 Interior 053, Nueva Indonesia, SLP 33946-8246"
    }
]